{
  "basics": {
    "name": "Stella Grasshof",
    "label": "Assistant Professor",
    "image": "",
    "email": "stgr@itu.dk",
    "url": "https://stellagra.github.io/",
    "summary": "Born in Germany, working in Denmark as an Assistant Professor in the Computer Science Department at the IT University of Copenhagen.",
    "location": {
      "city": "Copenhagen",
      "countryCode": "DK",
      "region": "Denmark"
    }
  },
  "education": [
    {
      "institution": "TNT, Leibniz Universität Hannover",
      "location": "Hannover, Germany",
      "url": "https://www.tnt.uni-hannover.de",
      "area": "Mathematics and Computer Science",
      "studyType": "PhD",
      "startDate": "2012-04",
      "endDate": "2019-11"
    }
  ],
  "languages": [
    {
      "language": "German",
      "fluency": "Native speaker",
      "icon": ""
    },
    {
      "language": "English",
      "fluency": "Fluent",
      "icon": ""
    }
  ],
  "interests": [
    {
      "name": "Machine Learning",
      "icon": "fa-solid fa-tag",
      "keywords": [
        "Non-rigid Structure from Motion",
        "3D reconstruction",
        "Factorisation",
        "Human Motion",
        "Mental Health applications"
      ]
    }
  ]
}